README.md
setup.py
bin/jira
jeera.egg-info/PKG-INFO
jeera.egg-info/SOURCES.txt
jeera.egg-info/dependency_links.txt
jeera.egg-info/requires.txt
jeera.egg-info/top_level.txt
jira/__init__.py