Metadata-Version: 2.1
Name: jeera
Version: 0.2
Summary: CLI for jira for its dumb shenannigans
Home-page: UNKNOWN
Author: Chris Lee
Author-email: chris@indico.io
License: UNKNOWN
Platform: UNKNOWN
Provides-Extra: test
